[
  {
    "timestamp": "2026-01-20T19:54:10.803389",
    "lesson_id": 1,
    "topic": "النباتات: .",
    "questions": [
      {
        "question_ar": "النبات بياكل إيه عشان يكبر ويبقى قوي؟",
        "correct_answer_ar": "ضوء الشمس",
        "options_ar": [
          "الميه",
          "الهوا",
          "ضوء الشمس"
        ]
      },
      {
        "question_ar": "لو النبات مش لاقي ميه أو هوا أو شمس كفاية، إيه اللي ممكن يحصل له؟",
        "correct_answer_ar": "هيموت",
        "options_ar": [
          "هينام كتير",
          "هيزعل بس",
          "هيموت"
        ]
      }
    ]
  }
]